smyte_pylib/__init__.py
smyte_pylib/decorators.py
smyte_pylib/main_loop.py
smyte_pylib/pacer.py
smyte_pylib/kafka/__init__.py
smyte_pylib/kafka/helpers.py
smyte_pylib/kafka/loop.py
smyte_pylib-0.2.3.dist-info/DESCRIPTION.rst
smyte_pylib-0.2.3.dist-info/METADATA
smyte_pylib-0.2.3.dist-info/RECORD
smyte_pylib-0.2.3.dist-info/WHEEL
smyte_pylib-0.2.3.dist-info/metadata.json
smyte_pylib-0.2.3.dist-info/top_level.txt
