Metadata-Version: 2.0
Name: smyte-pylib
Version: 0.2.3
Summary: Public python helpers in use by Smytes open source releases
Home-page: https://github.com/smyte/smyte_pylib
Author: Josh Yudaken
Author-email: josh@smyte.com
License: Apache Software License 2.0
Keywords: smyte_pylib
Platform: UNKNOWN
Classifier: Development Status :: 2 - Pre-Alpha
Classifier: Intended Audience :: Developers
Classifier: License :: OSI Approved :: Apache Software License
Classifier: Natural Language :: English
Classifier: Programming Language :: Python :: 2
Classifier: Programming Language :: Python :: 2.6
Classifier: Programming Language :: Python :: 2.7
Classifier: Programming Language :: Python :: 3
Classifier: Programming Language :: Python :: 3.3
Classifier: Programming Language :: Python :: 3.4
Classifier: Programming Language :: Python :: 3.5
Requires-Dist: pysigset
